async_tools/__init__.py
async_tools/asyncio.py
async_tools/sync.py
async_sync_tools-0.0.3.dist-info/LICENSE
async_sync_tools-0.0.3.dist-info/METADATA
async_sync_tools-0.0.3.dist-info/WHEEL
async_sync_tools-0.0.3.dist-info/top_level.txt
async_sync_tools-0.0.3.dist-info/RECORD
